CHANGELOG
LICENSE
MANIFEST.in
README.md
setup.py
geoprisma_config/__init__.py
geoprisma_config/admin.py
geoprisma_config/context_processors.py
geoprisma_config/forms.py
geoprisma_config/models.py
geoprisma_config/tests.py
geoprisma_config/urls.py
geoprisma_config/utils.py
geoprisma_config/views.py
geoprisma_config/widgets.py
geoprisma_config.egg-info/PKG-INFO
geoprisma_config.egg-info/SOURCES.txt
geoprisma_config.egg-info/dependency_links.txt
geoprisma_config.egg-info/top_level.txt
geoprisma_config/conf/__init__.py
geoprisma_config/conf/__init__.pyc
geoprisma_config/conf/types.py
geoprisma_config/conf/types.pyc
geoprisma_config/management/__init__.py
geoprisma_config/management/commands/__init__.py
geoprisma_config/management/commands/import.py
geoprisma_config/static/admin/gc_css/base.css
geoprisma_config/static/admin/gc_css/changelists.css
geoprisma_config/static/admin/gc_css/dashboard.css
geoprisma_config/static/admin/gc_css/forms.css
geoprisma_config/static/admin/gc_css/ie.css
geoprisma_config/static/admin/gc_css/login.css
geoprisma_config/static/admin/gc_css/rtl.css
geoprisma_config/static/admin/gc_css/widgets.css
geoprisma_config/static/admin/gc_img/admin/arrow-down.gif
geoprisma_config/static/admin/gc_img/admin/arrow-up.gif
geoprisma_config/static/admin/gc_img/admin/changelist-bg.gif
geoprisma_config/static/admin/gc_img/admin/changelist-bg_rtl.gif
geoprisma_config/static/admin/gc_img/admin/chooser-bg.gif
geoprisma_config/static/admin/gc_img/admin/chooser_stacked-bg.gif
geoprisma_config/static/admin/gc_img/admin/default-bg-reverse.gif
geoprisma_config/static/admin/gc_img/admin/default-bg.gif
geoprisma_config/static/admin/gc_img/admin/deleted-overlay.gif
geoprisma_config/static/admin/gc_img/admin/icon-no.gif
geoprisma_config/static/admin/gc_img/admin/icon-unknown.gif
geoprisma_config/static/admin/gc_img/admin/icon-yes.gif
geoprisma_config/static/admin/gc_img/admin/icon_addlink.gif
geoprisma_config/static/admin/gc_img/admin/icon_alert.gif
geoprisma_config/static/admin/gc_img/admin/icon_calendar.gif
geoprisma_config/static/admin/gc_img/admin/icon_changelink.gif
geoprisma_config/static/admin/gc_img/admin/icon_clock.gif
