Metadata-Version: 1.0
Name: geoprisma-config
Version: 0.0.2
Summary: A Django app to help configure a postgresql geoprisma system
Home-page: https://github.com/solution-globale-informatique/geoprisma_config
Author: Alexandre Lessard
Author-email: alexandrel@solutionglobale.com
License: BSD License
Platform: UNKNOWN
Classifier: Environment :: Web Environment
Classifier: Framework :: Django
Classifier: Intended Audience :: Developers
Classifier: License :: OSI Approved :: BSD License
Classifier: Operating System :: OS Independent
Classifier: Programming Language :: Python
Classifier: Programming Language :: Python :: 2.5
Classifier: Programming Language :: Python :: 2.6
Classifier: Programming Language :: Python :: 2.7
Classifier: Topic :: Internet :: WWW/HTTP
Classifier: Topic :: Internet :: WWW/HTTP :: Dynamic Content
